cazoo_logger/__init__.py
cazoo_logger/_version.py
cazoo_logger/contexts.py
cazoo_logger/formatters.py
cazoo_logger/lambda_support.py
cazoo_logger/logging_levels.py
cazoo_logger-0.9.0.dist-info/LICENCE
cazoo_logger-0.9.0.dist-info/METADATA
cazoo_logger-0.9.0.dist-info/WHEEL
cazoo_logger-0.9.0.dist-info/top_level.txt
cazoo_logger-0.9.0.dist-info/RECORD
