Metadata-Version: 2.1
Name: cazoo-logger
Version: 0.9.0
Summary: Super-opinionated structured logger for AWS lambda
Home-page: https://github.com/Cazoo-uk/py-logger
Author: Bob Gregory
Author-email: bob.gregory@cazoo.co.uk
License: MIT
Platform: UNKNOWN
